zmp_authentication_provider/__init__.py
zmp_authentication_provider/auth/__init__.py
zmp_authentication_provider/auth/basic_auth.py
zmp_authentication_provider/auth/oauth2_keycloak.py
zmp_authentication_provider/auth/session_auth.py
zmp_authentication_provider/db/basic_auth_user_repository.py
zmp_authentication_provider/db/oauth_user_repository.py
zmp_authentication_provider/exceptions.py
zmp_authentication_provider/routes/__init__.py
zmp_authentication_provider/routes/auth.py
zmp_authentication_provider/routes/basic_auth_user.py
zmp_authentication_provider/scheme/auth_model.py
zmp_authentication_provider/scheme/basicauth_request_model.py
zmp_authentication_provider/service/auth_service.py
zmp_authentication_provider/setting.py
zmp_authentication_provider/utils/encryption_utils.py
zmp_authentication_provider/utils/in_memory_session_store.py
zmp_authentication_provider/utils/redis_session_store.py
zmp_authentication_provider/utils/session_data.py
zmp_authentication_provider/utils/time_utils.py
zmp_authentication_provider-0.3.10.dist-info/LICENSE
zmp_authentication_provider-0.3.10.dist-info/METADATA
zmp_authentication_provider-0.3.10.dist-info/WHEEL
zmp_authentication_provider-0.3.10.dist-info/RECORD
